spdx_python_model/__init__.py
spdx_python_model/version.py
spdx_python_model/bindings/__init__.py
spdx_python_model/bindings/v3_0_1.py
spdx_python_model-0.0.4.dist-info/METADATA
spdx_python_model-0.0.4.dist-info/WHEEL
spdx_python_model-0.0.4.dist-info/licenses/LICENSE
spdx_python_model-0.0.4.dist-info/RECORD
