Metadata-Version: 2.4
Name: spdx_python_model
Version: 0.0.4
Summary: SPDX Model Python Bindings
Project-URL: Homepage, https://github.com/spdx/spdx-python-model
Project-URL: Repository, https://github.com/spdx/spdx-python-model.git
Project-URL: Issues, https://github.com/spdx/spdx-python-model/issues
Author-email: Joshua Watt <JPEWhacker@gmail.com>
License-Expression: Apache-2.0
License-File: LICENSE
Classifier: Development Status :: 4 - Beta
Classifier: Intended Audience :: Developers
Classifier: Programming Language :: Python :: 3
Classifier: Programming Language :: Python :: 3.9
Classifier: Programming Language :: Python :: 3.10
Classifier: Programming Language :: Python :: 3.11
Classifier: Programming Language :: Python :: 3.12
Classifier: Topic :: Software Development :: Libraries :: Python Modules
Requires-Python: >=3.9
Provides-Extra: dev
Requires-Dist: pytest>=7.4; extra == 'dev'
